weighted_metapath2vec/__init__.py
weighted_metapath2vec/model.py
weighted_metapath2vec/random_walk.py
weighted_metapath2vec-0.1.4.dist-info/LICENSE
weighted_metapath2vec-0.1.4.dist-info/WHEEL
weighted_metapath2vec-0.1.4.dist-info/METADATA
weighted_metapath2vec-0.1.4.dist-info/RECORD
