Metadata-Version: 2.1
Name: weighted-metapath2vec
Version: 0.1.4
Summary: A weighted alternative to metapath2vec for heterogenous graph embedding
Home-page: https://github.com/morteza/weighted-metapath2vec
License: MIT
Keywords: machine learning,graph embedding,metapath2vec
Author: Morteza Ansarinia
Author-email: ansarinia@me.com
Requires-Python: >=3.9,<3.11
Classifier: License :: OSI Approved :: MIT License
Classifier: Operating System :: OS Independent
Classifier: Programming Language :: Python :: 3
Classifier: Programming Language :: Python :: 3.10
Classifier: Programming Language :: Python :: 3.9
Classifier: Topic :: Software Development :: Libraries :: Python Modules
Requires-Dist: flake8 (>=4.0.1,<5.0.0)
Requires-Dist: gensim (>=4.1,<5.0)
Requires-Dist: networkx (>=2.8,<3.0)
Requires-Dist: scikit-learn (>=1.0,<2.0)
Project-URL: Repository, https://github.com/morteza/weighted-metapath2vec
